{
  "description": "Bowstring truss, span 15m, 10 bays, height 3.75m",
  "line_elements": [
    {
      "start": [
        0.0,
        0.0
      ],
      "end": [
        1.5,
        0.0
      ],
      "cross_section": "HEA100"
    },
    {
      "start": [
        1.5,
        0.0
      ],
      "end": [
        3.0,
        0.0
      ],
      "cross_section": "HEA100"
    },
    {
      "start": [
        3.0,
        0.0
      ],
      "end": [
        4.5,
        0.0
      ],
      "cross_section": "HEA100"
    },
    {
      "start": [
        4.5,
        0.0
      ],
      "end": [
        6.0,
        0.0
      ],
      "cross_section": "HEA100"
    },
    {
      "start": [
        6.0,
        0.0
      ],
      "end": [
        7.5,
        0.0
      ],
      "cross_section": "HEA100"
    },
    {
      "start": [
        7.5,
        0.0
      ],
      "end": [
        9.0,
        0.0
      ],
      "cross_section": "HEA100"
    },
    {
      "start": [
        9.0,
        0.0
      ],
      "end": [
        10.5,
        0.0
      ],
      "cross_section": "HEA100"
    },
    {
      "start": [
        10.5,
        0.0
      ],
      "end": [
        12.0,
        0.0
      ],
      "cross_section": "HEA100"
    },
    {
      "start": [
        12.0,
        0.0
      ],
      "end": [
        13.5,
        0.0
      ],
      "cross_section": "HEA100"
    },
    {
      "start": [
        13.5,
        0.0
      ],
      "end": [
        15.0,
        0.0
      ],
      "cross_section": "HEA100"
    },
    {
      "start": [
        1.5,
        1.35
      ],
      "end": [
        3.0,
        2.4000000000000004
      ],
      "cross_section": "HEA100"
    },
    {
      "start": [
        3.0,
        2.4000000000000004
      ],
      "end": [
        4.5,
        3.15
      ],
      "cross_section": "HEA100"
    },
    {
      "start": [
        4.5,
        3.15
      ],
      "end": [
        6.0,
        3.5999999999999996
      ],
      "cross_section": "HEA100"
    },
    {
      "start": [
        6.0,
        3.5999999999999996
      ],
      "end": [
        7.5,
        3.75
      ],
      "cross_section": "HEA100"
    },
    {
      "start": [
        7.5,
        3.75
      ],
      "end": [
        9.0,
        3.6
      ],
      "cross_section": "HEA100"
    },
    {
      "start": [
        9.0,
        3.6
      ],
      "end": [
        10.5,
        3.1500000000000004
      ],
      "cross_section": "HEA100"
    },
    {
      "start": [
        10.5,
        3.1500000000000004
      ],
      "end": [
        12.0,
        2.3999999999999995
      ],
      "cross_section": "HEA100"
    },
    {
      "start": [
        12.0,
        2.3999999999999995
      ],
      "end": [
        13.5,
        1.3499999999999996
      ],
      "cross_section": "HEA100"
    },
    {
      "start": [
        1.5,
        0.0
      ],
      "end": [
        1.5,
        1.35
      ],
      "cross_section": "HEA100"
    },
    {
      "start": [
        3.0,
        0.0
      ],
      "end": [
        3.0,
        2.4000000000000004
      ],
      "cross_section": "HEA100"
    },
    {
      "start": [
        4.5,
        0.0
      ],
      "end": [
        4.5,
        3.15
      ],
      "cross_section": "HEA100"
    },
    {
      "start": [
        6.0,
        0.0
      ],
      "end": [
        6.0,
        3.5999999999999996
      ],
      "cross_section": "HEA100"
    },
    {
      "start": [
        7.5,
        0.0
      ],
      "end": [
        7.5,
        3.75
      ],
      "cross_section": "HEA100"
    },
    {
      "start": [
        9.0,
        0.0
      ],
      "end": [
        9.0,
        3.6
      ],
      "cross_section": "HEA100"
    },
    {
      "start": [
        10.5,
        0.0
      ],
      "end": [
        10.5,
        3.1500000000000004
      ],
      "cross_section": "HEA100"
    },
    {
      "start": [
        12.0,
        0.0
      ],
      "end": [
        12.0,
        2.3999999999999995
      ],
      "cross_section": "HEA100"
    },
    {
      "start": [
        13.5,
        0.0
      ],
      "end": [
        13.5,
        1.3499999999999996
      ],
      "cross_section": "HEA100"
    }
  ],
  "support": [
    [
      0.0,
      0.0
    ],
    [
      15.0,
      0.0
    ]
  ],
  "loads": [
    [
      1.5,
      1.35,
      -473.85
    ],
    [
      3.0,
      2.4000000000000004,
      -947.7
    ],
    [
      4.5,
      3.15,
      -947.7
    ],
    [
      6.0,
      3.5999999999999996,
      -947.7
    ],
    [
      7.5,
      3.75,
      -947.7
    ],
    [
      9.0,
      3.6,
      -947.7
    ],
    [
      10.5,
      3.1500000000000004,
      -947.7
    ],
    [
      12.0,
      2.3999999999999995,
      -947.7
    ],
    [
      13.5,
      1.3499999999999996,
      -473.85
    ]
  ]
}