{
  "description": "Truss semantic outline — Interpreter output schema. Contains only what the Interpreter extracts and enriches from the user prompt. No sizing decisions, no algorithm parameters, no boundary condition types.",

  "required": [
    "geometry_truss"
  ],

  "properties": {

    "geometry_roof": {
      "description": "Overall roof envelope. Extracted from user prompt.",
      "properties": {
        "span_x_m": {
          "type": "number",
          "description": "Width of the roof in the span direction, in meters."
        },
        "length_y_m": {
          "type": "number",
          "description": "Length of the roof in the ridge direction, in meters."
        },
        "eave_height_m": {
          "type": "number",
          "description": "Wall/eave height at support level, in meters."
        },
        "max_ridge_height_m": {
          "type": "number",
          "description": "Maximum allowable roof peak height measured from eave level, in meters."
        },
        "min_clear_height_m": {
          "type": "number",
          "description": "Minimum interior clear height required below the bottom chord, in meters."
        },
        "truss_spacing_m": {
          "type": "number",
          "description": "Center-to-center spacing between trusses along the ridge direction, in meters."
        },
        "truss_count": {
          "type": "integer",
          "description": "Number of trusses along the ridge direction. Alternative to truss_spacing_m."
        }
      }
    },

    "geometry_truss": {
      "description": "Individual truss geometry and typology. Extracted from user prompt. Height is only set when the user states it; otherwise omit height_m and the Generator computes it from span and typology.",
      "required": ["span_m", "typology"],
      "properties": {
        "typology": {
          "enum": [
            "warren",
            "warren_with_verticals",
            "pratt",
            "howe",
            "fink",
            "flat",
            "bowstring",
            "parker",
            "camelback",
            "baltimore",
            "pennsylvania",
            "k_truss",
            "double_intersection_pratt",
            "double_intersection_warren",
            "lattice",
            "waddell_a_truss",
            "vierendeel",
            "custom_ground_structure"
          ],
          "description": "Truss typology stated or implied by the user."
        },
        "span_m": {
          "type": "number",
          "description": "Clear span of the truss in meters."
        },
        "height_m": {
          "type": "number",
          "description": "Height/rise of the truss from bottom to top chord at mid-span, in meters. Only include when the user explicitly states height; if omitted, the Generator computes it from span and typology (e.g. typical height/span ratios)."
        },
        "num_bays": {
          "type": "integer",
          "description": "Number of panel bays along the span, if stated by user."
        },
        "support_positions": {
          "type": "array",
          "description": "Support locations as [x, z] coordinate pairs. Boundary condition type is always pinned and set by the Generator.",
          "items": {
            "type": "array",
            "description": "[x, z] position in meters."
          }
        }
      }
    },

    "loads": {
      "description": "Load values. Combines what the user explicitly states with standard values the Interpreter fills in from engineering knowledge. Each value is tagged with its source so the Generator knows what was user-defined vs. assumed.",
      "properties": {

        "snow_kN_per_m2": {
          "type": "number",
          "description": "Characteristic snow load per m² of roof area."
        },
        "snow_source": {
          "enum": ["user_defined", "standard_assumed"],
          "description": "Indicates whether snow load was stated by user or filled in from standard assumptions."
        },

        "wind_pressure_kN_per_m2": {
          "type": "number",
          "description": "Wind pressure (positive = inward) per m² of roof surface."
        },
        "wind_suction_kN_per_m2": {
          "type": "number",
          "description": "Wind suction (outward) per m² of roof surface."
        },
        "wind_source": {
          "enum": ["user_defined", "standard_assumed"],
          "description": "Indicates whether wind load was stated by user or filled in from standard assumptions."
        },

        "roof_cladding_kN_per_m2": {
          "type": "number",
          "description": "Dead load from roof cladding and secondary structure per m²."
        },
        "cladding_source": {
          "enum": ["user_defined", "standard_assumed"],
          "description": "Indicates whether cladding load was stated by user or filled in from standard assumptions."
        },

        "additional_dead_kN_per_m2": {
          "type": "number",
          "description": "Any additional permanent loads stated by user, per m²."
        }
      }
    },

    "optimization_flags": {
      "description": "Optimization steps explicitly requested by the user. If not mentioned, Generator applies defaults from config.json.",
      "properties": {
        "node_positioning": {
          "type": "boolean",
          "description": "User requested node position optimization."
        },
        "member_topology": {
          "type": "boolean",
          "description": "User requested topology optimization (member removal)."
        },
        "member_sizing": {
          "type": "boolean",
          "description": "User requested cross-section sizing optimization."
        }
      }
    },

    "notes": {
      "type": "string",
      "description": "Any additional design intent or context from the user prompt that does not map to a structured field."
    }

  }
}
